{"word": "alarm", "levels": ["cet4", "cet6", "postgraduate", "senior", "toefl"], "translations": [{"translation": "惊恐，忧虑；警报", "types": ["n"]}, {"translation": "惊恐；忧虑；警报", "types": ["n"]}, {"translation": "使惊恐； 使担心", "types": ["vt"]}, {"translation": "惊恐，忧虑，警报", "types": ["n"]}, {"translation": "使惊恐， 使担心", "types": ["vt"]}, {"translation": "闹钟；警报，警告器；惊慌", "types": ["n"]}, {"translation": "警告；使惊恐", "types": ["v"]}, {"translation": "警报；惊恐， 惊慌", "types": ["n"]}, {"translation": "使惊恐， 惊动， 惊吓 A；向…报警； 警告", "types": ["vt"]}, {"translation": "警报", "types": ["n"]}, {"translation": "警报 vt恐吓, 警告", "types": ["n"]}, {"translation": "闹钟；警报", "types": ["n"]}], "phrases": [{"phrase": "alarm system", "translation": "报警系统"}, {"phrase": "fire alarm", "translation": "火警；火警警报器"}, {"phrase": "alarm clock", "translation": "闹钟"}, {"phrase": "false alarm", "translation": "假警报；引起一场空喜欢的人"}, {"phrase": "burglar alarm", "translation": "防窃报警器；防盗自动警铃"}, {"phrase": "fire alarm system", "translation": "火警信号系统；消防警报系统"}, {"phrase": "alarm bell", "translation": "警钟；警铃"}, {"phrase": "anti-theft alarm", "translation": "防盗警报系统"}, {"phrase": "false alarm rate", "translation": "火灾误报率；误警率；虚率"}, {"phrase": "alarm signal", "translation": "警报信号"}, {"phrase": "alarm device", "translation": "报警装置；告警装置"}, {"phrase": "gas alarm", "translation": "气体信号装置；瓦斯报警器；毒气警报"}, {"phrase": "alarm equipment", "translation": "报警器，报警信号装置；防盗报警设备"}, {"phrase": "ring the alarm", "translation": "拉警报，敲警钟"}, {"phrase": "burglar alarm system", "translation": "防盗警钟系统"}, {"phrase": "automatic fire alarm system", "translation": "火灾自动报警系统"}, {"phrase": "alarm circuit", "translation": "报警电路"}, {"phrase": "smoke alarm", "translation": "烟雾报警器"}, {"phrase": "in alarm", "translation": "惊慌，担心"}, {"phrase": "alarm message", "translation": "报警信息"}]}