{"word": "award", "levels": ["cet4", "cet6", "junior", "postgraduate", "senior", "toefl"], "translations": [{"translation": "授予；判给", "types": ["v"]}, {"translation": "奖（金）", "types": ["n"]}, {"translation": "奖，奖品；判定", "types": ["n"]}, {"translation": "授予， 给予； 判给， 裁定", "types": ["vt"]}, {"translation": "授予，给予；判给", "types": ["v"]}, {"translation": "奖， 奖品； 报酬， 津贴", "types": ["n"]}, {"translation": "授予；判定", "types": ["v"]}, {"translation": "奖品；判决", "types": ["n"]}, {"translation": "奖", "types": ["n"]}, {"translation": "授予， 奖给", "types": ["vt"]}, {"translation": "奖品， 奖励", "types": ["n"]}, {"translation": "奖,奖品", "types": ["n"]}, {"translation": "授予,判给", "types": ["v"]}], "phrases": [{"phrase": "academy award", "translation": "奥斯卡金像奖；学院奖（美国电影艺术科学院颁发的年度奖项）"}, {"phrase": "award ceremony", "translation": "颁奖仪式，颁奖典礼"}, {"phrase": "arbitral award", "translation": "仲裁裁决；公断书"}, {"phrase": "arbitration award", "translation": "仲裁裁决；公断书"}, {"phrase": "special award", "translation": "特别奖"}, {"phrase": "contract award", "translation": "合同判授"}, {"phrase": "national book award", "translation": "（美）国家图书奖"}, {"phrase": "final award", "translation": "终局性仲裁裁决"}, {"phrase": "grammy award", "translation": "格莱美奖（美国音乐奖项）"}]}