{"word": "baseball", "levels": ["cet4", "cet6", "junior", "postgraduate", "toefl"], "translations": [{"translation": "棒球", "types": ["n"]}, {"translation": "棒球运动；棒球", "types": ["n"]}, {"translation": "棒球（运动）", "types": ["n"]}], "phrases": [{"phrase": "baseball game", "translation": "棒球比赛"}, {"phrase": "baseball team", "translation": "棒球队；棒球队型"}, {"phrase": "baseball player", "translation": "棒球运动员；棒球选手"}, {"phrase": "baseball cap", "translation": "棒球帽"}, {"phrase": "baseball bat", "translation": "棒球棒"}, {"phrase": "major league baseball", "translation": "（美）职业棒球大联盟"}, {"phrase": "baseball glove", "translation": "棒球手套"}, {"phrase": "baseball diamond", "translation": "棒球内场"}]}