{"word": "brittle", "levels": ["cet4", "postgraduate", "sat", "toefl"], "translations": [{"translation": "脆的；易损坏的", "types": ["adj"]}, {"translation": "易碎的； 脆的", "types": ["adj"]}, {"translation": "易碎的，脆弱的；易生气的", "types": ["adj"]}, {"translation": "易碎的； 脆弱的", "types": ["adj"]}, {"translation": "易碎的, 脆弱的", "types": ["adj"]}, {"translation": "易碎的； 脆弱的； 尖利的", "types": ["adj"]}], "phrases": [{"phrase": "brittle fracture", "translation": "脆性破坏"}, {"phrase": "brittle material", "translation": "脆性物料"}, {"phrase": "brittle failure", "translation": "脆性破坏；脆性疲劳；脆性失败"}]}