{"word": "burden", "levels": ["cet4", "cet6", "postgraduate", "senior", "toefl"], "translations": [{"translation": "负担，包袱", "types": ["n"]}, {"translation": "担子，重担；装载量", "types": ["n"]}, {"translation": "重担，精神负担", "types": ["n"]}, {"translation": "加重压于， 烦扰； 负担， 装载", "types": ["vt"]}, {"translation": "负担", "types": ["n"]}, {"translation": "负担；责任；船的载货量", "types": ["n"]}, {"translation": "使负担；烦扰；装货于", "types": ["v"]}, {"translation": "担子，负担，重担", "types": ["n"]}, {"translation": "担子， 负担", "types": ["n"]}, {"translation": "担子, 负担", "types": ["n"]}, {"translation": "烦扰", "types": ["v"]}], "phrases": [{"phrase": "heavy burden", "translation": "重负；重炉料"}, {"phrase": "burden of proof", "translation": "举证责任；提供证据之责任"}, {"phrase": "tax burden", "translation": "课税负担"}, {"phrase": "financial burden", "translation": "n. 财政负担，经济负担"}, {"phrase": "economic burden", "translation": "经济负担"}, {"phrase": "beast of burden", "translation": "驮兽（如马、驴等）"}, {"phrase": "burden of persuasion", "translation": "说服责任；举证责任"}]}