{"word": "cake", "levels": ["cet4", "junior", "postgraduate", "senior"], "translations": [{"translation": "饼，糕，蛋糕", "types": ["n"]}, {"translation": "蛋糕；块状物；利益总额", "types": ["n"]}, {"translation": "使结块", "types": ["v"]}, {"translation": "饼， 糕， 蛋糕", "types": ["n"]}], "phrases": [{"phrase": "birthday cake", "translation": "生日蛋糕"}, {"phrase": "piece of cake", "translation": "轻而易举的事情；轻松愉快的事"}, {"phrase": "moon cake", "translation": "n. 月饼"}, {"phrase": "icing on the cake", "translation": "锦上添花"}, {"phrase": "chocolate cake", "translation": "巧克力蛋糕"}, {"phrase": "sell like hot cakes", "translation": "热销"}, {"phrase": "filter cake", "translation": "滤饼"}, {"phrase": "wedding cake", "translation": "n. 结婚蛋糕"}, {"phrase": "sponge cake", "translation": "松糕"}, {"phrase": "rice cake", "translation": "年糕"}, {"phrase": "cheese cake", "translation": "n. 干酪饼；富于性感的半裸体美女照"}, {"phrase": "bean cake", "translation": "豆饼；豆糟"}, {"phrase": "cakes and ale", "translation": "n. 欢乐"}, {"phrase": "tea cake", "translation": "茶点"}, {"phrase": "make a cake", "translation": "制做蛋糕"}, {"phrase": "take the cake", "translation": "得奖；坏到极点"}, {"phrase": "bake a cake", "translation": "烘蛋糕"}, {"phrase": "cream cake", "translation": "奶油蛋糕"}, {"phrase": "cake flour", "translation": "n. 细面粉"}, {"phrase": "seed cake", "translation": "种子饼；香饼"}]}