{"word": "clasp", "levels": ["cet4", "cet6", "postgraduate", "toefl"], "translations": [{"translation": "扣子，钩子；别针", "types": ["n"]}, {"translation": "扣住，扣紧，钩住", "types": ["v"]}, {"translation": "扣子，钩子；紧抱，紧握", "types": ["n"]}, {"translation": "抱紧， 握紧； 扣住， 扣紧", "types": ["vt"]}, {"translation": "扣子，钩子；握手", "types": ["n"]}, {"translation": "紧抱；扣紧；紧紧缠绕", "types": ["v"]}, {"translation": "扣住， 钩住；紧握， 紧抱", "types": ["v"]}, {"translation": "握手； 拥抱；扣子， 钩子", "types": ["n"]}, {"translation": "搭扣，扣环；紧抱；紧握", "types": ["n"]}, {"translation": "握紧； 抱紧； 扣住， 扣牢", "types": ["vt"]}], "phrases": []}