{"word": "collect", "levels": ["cet4", "junior", "postgraduate", "senior", "toefl"], "translations": [{"translation": "收集", "types": ["v"]}, {"translation": "收款", "types": ["v"]}, {"translation": "收集；募捐", "types": ["v"]}, {"translation": "由收件人付款地", "types": ["adv"]}, {"translation": "由收件人付款的", "types": ["adj"]}, {"translation": "（Collect）人名；（英）科莱克特", "types": ["n"]}, {"translation": "收集，采集；收；领取；聚集，汇集", "types": ["v"]}, {"translation": "由对方付费的", "types": ["adj"]}, {"translation": "收集,搜集;领取,接走;收（税等）;聚集,堆积", "types": ["v"]}, {"translation": "收集， 搜集", "types": ["v"]}], "phrases": [{"phrase": "collect oneself", "translation": "镇定下来，使自己平心静气"}, {"phrase": "collect data", "translation": "收集资料"}, {"phrase": "collect money", "translation": "集资；筹钱"}, {"phrase": "collect call", "translation": "对方付费电话"}, {"phrase": "freight collect (freight payable at destination)", "translation": "运费到付（到目的地后付运费）"}, {"phrase": "freight collect", "translation": "运费到付"}, {"phrase": "collect stamps", "translation": "集邮"}, {"phrase": "collect from", "translation": "向…收款；从…处收集"}, {"phrase": "freight to collect", "translation": "运费到付"}, {"phrase": "collect leaves", "translation": "收集树叶"}]}