{"word": "denial", "levels": ["cet6", "postgraduate", "toefl"], "translations": [{"translation": "否定；拒绝相信", "types": ["n"]}, {"translation": "否认； 拒绝， 拒绝给予", "types": ["n"]}, {"translation": "否认；拒绝；节制；背弃", "types": ["n"]}, {"translation": "否认；拒绝； 拒绝给予", "types": ["n"]}, {"translation": "否认,谢绝", "types": ["n"]}], "phrases": [{"phrase": "denial of service", "translation": "拒绝服务"}, {"phrase": "in denial", "translation": "否认；拒绝接受现实；拒绝承认出了问题"}, {"phrase": "denial of service attack", "translation": "拒绝服务攻击；阻断服务攻击"}]}