{"word": "dig", "levels": ["cet4", "junior", "postgraduate", "senior", "toefl"], "translations": [{"translation": "掘，挖；采掘", "types": ["v"]}, {"translation": "挖（土等），掘（洞）", "types": ["v"]}, {"translation": "挖苦，嘲讽", "types": ["n"]}, {"translation": "挖，掘；探究", "types": ["v"]}, {"translation": "戳，刺；挖苦", "types": ["n"]}, {"translation": "挖  ， 掘", "types": ["v"]}, {"translation": "挖", "types": ["v"]}], "phrases": [{"phrase": "dig out", "translation": "掘出；发现"}, {"phrase": "dig deep", "translation": "◎挖深"}, {"phrase": "dig up", "translation": "挖出；掘起；开垦；发现"}, {"phrase": "dig in", "translation": "掘土以掺进；掘土把…埋起来；【口】开始认真工作；【军】掘壕固守"}, {"phrase": "dig into", "translation": "v. 钻研；掘进去"}, {"phrase": "dig a hole", "translation": "挖坑"}, {"phrase": "dig at", "translation": "挖苦；讽刺"}, {"phrase": "dig down", "translation": "vt. 掏腰包；挖下；掘倒"}]}