{"word": "dilute", "levels": ["cet6", "postgraduate", "sat", "toefl"], "translations": [{"translation": "稀释，冲淡", "types": ["v"]}, {"translation": "稀释的， 冲淡的", "types": ["adj"]}, {"translation": "稀释，冲淡", "types": ["vt"]}, {"translation": "稀释的；淡的", "types": ["adj"]}, {"translation": "稀释；冲淡；削弱", "types": ["v"]}, {"translation": "冲淡的， 稀释的", "types": ["adj"]}, {"translation": "冲淡， 稀释", "types": ["vt"]}, {"translation": "冲淡，稀释", "types": ["vt"]}, {"translation": "冲淡的，稀释的", "types": ["adj"]}, {"translation": "冲淡， 稀释； 淡化， 削弱", "types": ["vt"]}], "phrases": [{"phrase": "dilute solution", "translation": "【化】稀溶液"}, {"phrase": "dilute acid", "translation": "稀酸"}, {"phrase": "dilute hydrochloric acid", "translation": "稀盐酸"}, {"phrase": "dilute phase", "translation": "【化】稀相"}, {"phrase": "dilute sulphuric acid", "translation": "稀硫酸"}, {"phrase": "dilute with", "translation": "用…冲淡；用…稀释"}]}