{"word": "engine", "levels": ["cet4", "cet6", "postgraduate", "senior", "toefl"], "translations": [{"translation": "引擎，发动机", "types": ["n"]}, {"translation": "发动机，引擎；机车", "types": ["n"]}, {"translation": "引擎， 发动机； 机车", "types": ["n"]}, {"translation": "引擎，发动机；机车，火车头；工具", "types": ["n"]}, {"translation": "发动机， 引擎；火车头", "types": ["n"]}, {"translation": "发动机， 引擎", "types": ["n"]}, {"translation": "发动机,引擎", "types": ["n"]}], "phrases": [{"phrase": "diesel engine", "translation": "柴油机（等于diesel）"}, {"phrase": "search engine", "translation": "搜索引擎"}, {"phrase": "gasoline engine", "translation": "汽油机，汽油发动机"}, {"phrase": "engine oil", "translation": "机器润滑油"}, {"phrase": "combustion engine", "translation": "内燃机；燃烧机；内燃机燃烧机"}, {"phrase": "internal combustion engine", "translation": "内燃机"}, {"phrase": "main engine", "translation": "主机，主发动机"}, {"phrase": "engine room", "translation": "轮机舱"}, {"phrase": "engine performance", "translation": "引擎性能"}, {"phrase": "rocket engine", "translation": "n. 火箭发动机；火箭引擎"}, {"phrase": "engine cylinder", "translation": "发动机汽缸"}, {"phrase": "steam engine", "translation": "蒸汽机"}, {"phrase": "automobile engine", "translation": "汽车发动机引擎"}, {"phrase": "engine parts", "translation": "发动机部件"}, {"phrase": "gas engine", "translation": "内燃机；燃气发动机"}, {"phrase": "engine power", "translation": "发动机功率；额定功率"}, {"phrase": "engine speed", "translation": "发动机转速度；引擎转速"}, {"phrase": "internal-combustion engine", "translation": "内燃机"}, {"phrase": "inference engine", "translation": "【计】推理机"}, {"phrase": "motorcycle engine", "translation": "摩托车发动机；摩托车引擎"}]}