{"word": "evolutionary", "levels": ["cet4", "toefl"], "translations": [{"translation": "演变的，进化的", "types": ["adj"]}, {"translation": "进化的,发展的,演变的", "types": ["adj"]}], "phrases": [{"phrase": "evolutionary process", "translation": "进化过程，演化过程"}, {"phrase": "evolutionary biology", "translation": "进化生物学"}, {"phrase": "evolutionary psychology", "translation": "进化心理学；演化心理學"}, {"phrase": "evolutionary tree", "translation": "进化树"}, {"phrase": "evolutionary anthropology", "translation": "进化人类学；演化的人类学"}]}