{"word": "exhibition", "levels": ["cet4", "junior", "postgraduate", "senior", "toefl"], "translations": [{"translation": "展览", "types": ["n"]}, {"translation": "展览，陈列；展览会", "types": ["n"]}, {"translation": "展览，显示；展览会；展览品", "types": ["n"]}, {"translation": "展览， 展览会； 展品", "types": ["n"]}, {"translation": "表现,展览会", "types": ["n"]}], "phrases": [{"phrase": "exhibition hall", "translation": "展览厅"}, {"phrase": "art exhibition", "translation": "艺术展览；美术展览"}, {"phrase": "exhibition centre", "translation": "展览中心"}, {"phrase": "exhibition area", "translation": "展区；参展面积"}, {"phrase": "on exhibition", "translation": "展出中"}, {"phrase": "exhibition room", "translation": "展览室，陈列室"}, {"phrase": "exhibition game", "translation": "n. 表演赛"}, {"phrase": "exhibition building", "translation": "展览馆；展示馆"}, {"phrase": "exhibition match", "translation": "表演赛"}]}