{"word": "flesh", "levels": ["cet4", "postgraduate", "senior", "toefl"], "translations": [{"translation": "肉，肌肉；肉体", "types": ["n"]}, {"translation": "肉， 肌肉， 肉体", "types": ["n"]}, {"translation": "肉；肉体", "types": ["n"]}, {"translation": "喂肉给…；使发胖", "types": ["v"]}, {"translation": "肉", "types": ["n"]}, {"translation": "肉， 肉体", "types": ["n"]}, {"translation": "肉，果肉", "types": ["n"]}], "phrases": [{"phrase": "flesh and blood", "translation": "血肉之躯；人类；情欲"}, {"phrase": "in the flesh", "translation": "本人；亲自；以肉体形式"}, {"phrase": "all flesh", "translation": "众生；人类"}, {"phrase": "after the flesh", "translation": "世俗地，粗俗地"}, {"phrase": "pound of flesh", "translation": "合乎法律的无礼要求"}, {"phrase": "in flesh", "translation": "肥胖"}, {"phrase": "gain flesh", "translation": "发胖；长肉"}, {"phrase": "flesh out", "translation": "充实，具体化"}, {"phrase": "flesh wound", "translation": "轻伤，皮肉之伤；皮肉伤"}, {"phrase": "become one flesh", "translation": "成为一体"}]}