{"word": "flow", "levels": ["cet4", "postgraduate", "senior", "toefl"], "translations": [{"translation": "流动", "types": ["n", "v"]}, {"translation": "流动；飘垂；涨潮", "types": ["v"]}, {"translation": "流动，涌流；川流不息；飘扬", "types": ["v"]}, {"translation": "流动；流量；涨潮，泛滥", "types": ["n"]}, {"translation": "流动", "types": ["v"]}, {"translation": "流， 流动", "types": ["n"]}, {"translation": "流动,淹没", "types": ["n", "v"]}], "phrases": [{"phrase": "flow in", "translation": "流入"}, {"phrase": "flow field", "translation": "流场，痢"}, {"phrase": "flow rate", "translation": "流量；流速"}, {"phrase": "process flow", "translation": "工序流程"}, {"phrase": "cash flow", "translation": "资金流动"}, {"phrase": "blood flow", "translation": "血流；血流量"}, {"phrase": "flow chart", "translation": "n. 流程图；生产过程图解；作业图"}, {"phrase": "gas flow", "translation": "气流；气流量"}, {"phrase": "traffic flow", "translation": "交通流量"}, {"phrase": "fluid flow", "translation": "流体流动"}, {"phrase": "air flow", "translation": "气流；空气流量；空气流向"}, {"phrase": "water flow", "translation": "水流；水流量"}, {"phrase": "information flow", "translation": "信息流；数据流"}, {"phrase": "power flow", "translation": "功率流；电力潮流"}, {"phrase": "flow velocity", "translation": "流速"}, {"phrase": "work flow", "translation": "工作流程；生产流程"}, {"phrase": "flow control", "translation": "流控制"}, {"phrase": "flow pattern", "translation": "流型，流动型态；活动模；流线谱"}, {"phrase": "material flow", "translation": "n. 物料流，物质流；原料周转"}, {"phrase": "data flow", "translation": "数据流"}]}