{"word": "independence", "levels": ["cet4", "cet6", "postgraduate", "senior", "toefl"], "translations": [{"translation": "独立，自主，自立", "types": ["n"]}, {"translation": "独立， 自主， 自立", "types": ["n"]}, {"translation": "独立； 自主； 自立", "types": ["n"]}, {"translation": "独立， 自主", "types": ["n"]}, {"translation": "独立性，自立性；自主", "types": ["n"]}, {"translation": "独立", "types": ["n"]}, {"translation": "独立,自主", "types": ["n"]}], "phrases": [{"phrase": "independence from", "translation": "独立自主"}, {"phrase": "declaration of independence", "translation": "独立宣言"}, {"phrase": "independence day", "translation": "美国独立纪念日（7月4日）"}, {"phrase": "economic independence", "translation": "经济上的独立"}, {"phrase": "war of independence", "translation": "n. 独立战争"}, {"phrase": "functional independence", "translation": "函数无关"}, {"phrase": "mutual independence", "translation": "相互独立"}, {"phrase": "linear independence", "translation": "线性无关；线性独立"}, {"phrase": "platform independence", "translation": "平台独立，平台无关"}, {"phrase": "independence hall", "translation": "独立大厅（位于美国费城，独立宣言签字处）"}]}