{"word": "knob", "levels": ["cet4", "cet6", "postgraduate"], "translations": [{"translation": "门把，拉手；旋纽", "types": ["n"]}, {"translation": "球形把手， 球形柄； 旋钮； 小块", "types": ["n"]}, {"translation": "把手；瘤；球形突出物", "types": ["n"]}, {"translation": "鼓起", "types": ["vi"]}, {"translation": "使有球形突出物", "types": ["vt"]}, {"translation": "门把手， 把手； 旋钮", "types": ["n"]}], "phrases": [{"phrase": "with knobs on", "translation": "【俚语】尤其突出地，更加"}, {"phrase": "door knob", "translation": "门把手；门把捏手"}, {"phrase": "adjusting knob", "translation": "调节旋钮"}, {"phrase": "control knob", "translation": "控制旋钮；调节炳"}]}