{"word": "limp", "levels": ["cet4", "cet6", "postgraduate"], "translations": [{"translation": "软的；不强壮的", "types": ["adj"]}, {"translation": "〔因一腿受伤而〕跛行，一瘸一拐地走", "types": ["v"]}, {"translation": "跛行", "types": ["n"]}, {"translation": "蹒跚，跛行", "types": ["v"]}, {"translation": "一瘸一拐地走，蹒跚", "types": ["vi"]}, {"translation": "软弱的，无生气的，无精神的；软的，松沓的", "types": ["adj"]}, {"translation": "柔软的，无力的；软弱的", "types": ["adj"]}, {"translation": "跛行，一拐一拐地走；缓慢费力地前进", "types": ["v"]}, {"translation": "柔软的， 易曲的， 无力的", "types": ["adj"]}, {"translation": "/", "types": ["n"]}], "phrases": []}