{"word": "lion", "levels": ["cet4", "junior", "postgraduate", "senior", "toefl"], "translations": [{"translation": "狮子；勇猛的人", "types": ["n"]}, {"translation": "狮子；名人；勇猛的人；社交场合的名流", "types": ["n"]}, {"translation": "狮子", "types": ["n"]}], "phrases": [{"phrase": "lion dance", "translation": "舞狮"}, {"phrase": "sea lion", "translation": "n. 【动】海狮"}, {"phrase": "great lion", "translation": "名人，名流；备受欢迎的人"}, {"phrase": "mountain lion", "translation": "【动】美洲狮（等于cougar）"}, {"phrase": "lion tamer", "translation": "驯狮者"}, {"phrase": "see the lions", "translation": "看狮子；游览名胜"}, {"phrase": "lion head", "translation": "狮子兔（产地主要在荷兰和美国）"}]}