{"word": "overcome", "levels": ["cet4", "cet6", "postgraduate", "sat", "senior", "toefl"], "translations": [{"translation": "战胜，克服", "types": ["v"]}, {"translation": "战胜， 克服； 压倒， 使受不了", "types": ["vt"]}, {"translation": "克服；胜过", "types": ["v"]}, {"translation": "战胜， 克服", "types": ["vt"]}, {"translation": "战胜， 克服， 胜过； 征服", "types": ["v"]}, {"translation": "战胜， 克服， 胜过", "types": ["v"]}, {"translation": "战胜,克服", "types": ["v"]}], "phrases": [{"phrase": "overcome difficulties", "translation": "克服困难；战胜困难"}]}