{"word": "own", "levels": ["cet4", "junior", "senior"], "translations": [{"translation": "自己的", "types": ["adj"]}, {"translation": "有，拥有", "types": ["v"]}, {"translation": "拥有；承认", "types": ["v"]}, {"translation": "自己的；特有的", "types": ["adj"]}, {"translation": "自己的", "types": ["n"]}, {"translation": "有， 拥有", "types": ["v"]}, {"translation": "拥有", "types": ["vt"]}], "phrases": [{"phrase": "your own", "translation": "你自己的"}, {"phrase": "on their own", "translation": "凭自己的力量，他们自己；静静独处"}, {"phrase": "of his own", "translation": "他自己的；属于他自己的"}, {"phrase": "of your own", "translation": "adj. 你自己的"}, {"phrase": "on your own", "translation": "独立地， 自愿地"}, {"phrase": "own brand", "translation": "自有品牌；使用自己商标的商品"}, {"phrase": "on his own", "translation": "独立地；单刀"}, {"phrase": "on my own", "translation": "靠自己；独自一人；一己之力"}, {"phrase": "of one's own", "translation": "属于某人自己的"}, {"phrase": "on our own", "translation": "adv. 凭我们自己"}, {"phrase": "on one's own", "translation": "adv. 独立地；独自地；主动地"}, {"phrase": "own risk", "translation": "个人承担风险"}, {"phrase": "own one's feelings", "translation": "接受、承认个人的真实情感"}, {"phrase": "own goal", "translation": "影响本身利益的错误行为；【足球】误中本队球门"}, {"phrase": "own weight", "translation": "自重"}, {"phrase": "at your own risk", "translation": "由自己负责"}, {"phrase": "in their own right", "translation": "凭他们本身的实力"}, {"phrase": "mind your own business", "translation": "别多管闲事"}, {"phrase": "own up", "translation": "v. 坦白；爽快承认"}, {"phrase": "make one's own", "translation": "把…看做是自己的"}]}