{"word": "pension", "levels": ["cet4", "cet6", "postgraduate", "sat", "senior"], "translations": [{"translation": "养老金", "types": ["n"]}, {"translation": "养老金，抚恤金", "types": ["n"]}, {"translation": "发给…养老金", "types": ["vt"]}, {"translation": "养老金,年金", "types": ["n"]}, {"translation": "退休金，抚恤金；津贴；膳宿费", "types": ["n"]}, {"translation": "发给养老金或抚恤金", "types": ["v"]}, {"translation": "养老金， 年金", "types": ["n"]}], "phrases": [{"phrase": "pension fund", "translation": "养老基金；退休基金"}, {"phrase": "pension insurance", "translation": "养老保险"}, {"phrase": "pension plan", "translation": "公积金计划；退休金办法；养老计划"}, {"phrase": "old-age pension", "translation": "养老金；退休金"}, {"phrase": "pension scheme", "translation": "退休金计划"}, {"phrase": "retirement pension", "translation": "退休金，养老金"}, {"phrase": "old age pension", "translation": "养老金；退休金"}, {"phrase": "supplementary pension", "translation": "企业年金；辅助退休金"}]}