{"word": "plaster", "levels": ["cet6", "postgraduate", "toefl"], "translations": [{"translation": "灰浆，灰泥；石膏；橡皮膏，膏药", "types": ["n"]}, {"translation": "在…上抹灰泥， 厚厚地涂抹", "types": ["vt"]}, {"translation": "石膏；灰泥；膏药", "types": ["n"]}, {"translation": "减轻；粘贴；涂以灰泥；敷以膏药；使平服", "types": ["v"]}, {"translation": "灰泥； 熟石膏； 膏药 <", "types": ["n"]}, {"translation": "石膏 vt敷以膏药", "types": ["n"]}, {"translation": "在…上抹灰泥， 厚厚地涂", "types": ["v"]}, {"translation": "灰浆，灰泥，石膏", "types": ["n"]}], "phrases": [{"phrase": "in plaster", "translation": "上石膏"}, {"phrase": "adhesive plaster", "translation": "橡皮膏"}, {"phrase": "plaster cast", "translation": "石膏绷带；石膏模型"}, {"phrase": "plaster board", "translation": "n. 灰泥板；灰胶纸柏板；糊墙纸板"}, {"phrase": "plaster mold", "translation": "石膏模型"}, {"phrase": "gypsum plaster", "translation": "石膏灰泥，石膏抹面；石膏胶凝材料；粉饰用石膏粉"}, {"phrase": "sticking plaster", "translation": "橡皮膏"}, {"phrase": "plaster of paris", "translation": "熟石膏；烧石膏"}, {"phrase": "plaster model", "translation": "n. 石膏模型；石膏像"}, {"phrase": "wall plaster", "translation": "刷墙粉"}, {"phrase": "gypsum plaster board", "translation": "石膏板；石膏灰泥板"}, {"phrase": "plaster work", "translation": "抹灰泥工作；抹灰工事"}]}