{"word": "portfolio", "levels": ["postgraduate", "sat"], "translations": [{"translation": "公文包；文件夹； 作品集；投资组合", "types": ["n"]}, {"translation": "公文包；文件夹；证券投资组合；部长职务", "types": ["n"]}, {"translation": "文件夹； 公事包", "types": ["n"]}], "phrases": [{"phrase": "investment portfolio", "translation": "投资证券组合"}, {"phrase": "portfolio investment", "translation": "笼统有价证券投资；间接投资"}, {"phrase": "product portfolio", "translation": "产品组合；产品系列"}, {"phrase": "portfolio selection", "translation": "组合证券投资选择；【经】笼统投资选择"}, {"phrase": "portfolio management", "translation": "组合管理；资产组合管理；证券投资管理"}, {"phrase": "portfolio theory", "translation": "最佳证券投资理论"}, {"phrase": "portfolio assessment", "translation": "档案评估"}, {"phrase": "portfolio risk", "translation": "证券组合投资风险"}, {"phrase": "asset portfolio", "translation": "资产组合"}, {"phrase": "portfolio manager", "translation": "投资组合经理；组合基金经理；有价证券管理人"}, {"phrase": "portfolio strategy", "translation": "投资组合战略"}]}