{"word": "precious", "levels": ["cet4", "cet6", "postgraduate", "senior", "toefl"], "translations": [{"translation": "珍贵的，宝贵的", "types": ["adj"]}, {"translation": "珍贵的， 宝贵的", "types": ["adj"]}, {"translation": "珍贵的,贵重的", "types": ["adj"]}, {"translation": "宝贵的；珍贵的；矫揉造作的", "types": ["adj"]}, {"translation": "（Precious）人名；（英）普雷舍斯，普雷舍丝（女名）", "types": ["n"]}, {"translation": "珍贵的； 贵重的", "types": ["adj"]}, {"translation": "宝贵的， 珍贵的", "types": ["adj"]}, {"translation": "宝贵的,珍爱的", "types": ["adj"]}, {"translation": "贵重的； 珍爱的", "types": ["adj"]}], "phrases": [{"phrase": "precious metal", "translation": "贵金属，贵重金属"}, {"phrase": "precious stone", "translation": "宝石"}, {"phrase": "precious moment", "translation": "珍贵的时刻"}]}