{"word": "productive", "levels": ["cet4", "cet6", "postgraduate", "sat", "toefl"], "translations": [{"translation": "富有成效的", "types": ["adj"]}, {"translation": "生产的；出产…的", "types": ["adj"]}, {"translation": "多产的， 富饶的； 富有成效的", "types": ["adj"]}, {"translation": "生产（性）的,能产的,多产的", "types": ["adj"]}, {"translation": "能生产的；生产的，生产性的；多产的；富有成效的", "types": ["adj"]}, {"translation": "生产的， 能产的； 多产的", "types": ["adj"]}, {"translation": "生产  的； 能产的， 多产的", "types": ["adj"]}, {"translation": "生产的； 能产的， 多产的； 富有成效的", "types": ["adj"]}], "phrases": [{"phrase": "productive forces", "translation": "生产力"}, {"phrase": "productive capacity", "translation": "生产能力"}, {"phrase": "productive efficiency", "translation": "生产效率；生产效能"}, {"phrase": "productive maintenance", "translation": "生产维修"}, {"phrase": "productive time", "translation": "运算时间；生产时间"}, {"phrase": "total productive maintenance", "translation": "全面生产维护"}, {"phrase": "productive investment", "translation": "生产性投资"}]}