{"word": "progressive", "levels": ["cet4", "cet6", "postgraduate", "toefl"], "translations": [{"translation": "进步的；向前进的", "types": ["adj"]}, {"translation": "前进的； 渐进的； 进行式的", "types": ["adj"]}, {"translation": "进步的,先进的;前进的", "types": ["adj"]}, {"translation": "进步的；先进的", "types": ["adj"]}, {"translation": "改革论者；进步分子", "types": ["n"]}, {"translation": "进步的， 先进的； 前进的", "types": ["adj"]}, {"translation": "先进的,前进的", "types": ["adj"]}, {"translation": "进步分子", "types": ["n"]}, {"translation": "进步的； 逐步的， 渐进的； 【语】进行时的", "types": ["adj"]}], "phrases": [{"phrase": "progressive die", "translation": "【机】级进模；顺序冲模"}, {"phrase": "progressive party", "translation": "美国进步党"}, {"phrase": "democratic progressive party", "translation": "民进党"}, {"phrase": "progressive development", "translation": "n. 前进发展"}, {"phrase": "progressive cavity pump", "translation": "螺杆泵；螺杆抽油泵"}, {"phrase": "progressive forces", "translation": "进步力量"}, {"phrase": "progressive tax", "translation": "累进税"}, {"phrase": "progressive movement", "translation": "进步运动；渐进运动"}, {"phrase": "progressive scan", "translation": "逐行扫描"}, {"phrase": "progressive rate", "translation": "累进税率"}]}