{"word": "protection", "levels": ["cet4", "senior", "toefl"], "translations": [{"translation": "保护，警戒", "types": ["n"]}, {"translation": "保护， 防护", "types": ["n"]}, {"translation": "保护；防卫；护照", "types": ["n"]}, {"translation": "保护", "types": ["n"]}], "phrases": [{"phrase": "environmental protection", "translation": "环境保护"}, {"phrase": "environment protection", "translation": "环境保护；环境保扩"}, {"phrase": "protection system", "translation": "保护系统"}, {"phrase": "fire protection", "translation": "消防；消防处"}, {"phrase": "legal protection", "translation": "法律保护；合法保护"}, {"phrase": "health protection", "translation": "卫生防护；保健品"}, {"phrase": "relay protection", "translation": "继电保护"}, {"phrase": "cathodic protection", "translation": "阴极保护"}, {"phrase": "corrosion protection", "translation": "防腐"}, {"phrase": "lightning protection", "translation": "防雷法"}, {"phrase": "protection device", "translation": "保护设备；防护设备"}, {"phrase": "labor protection", "translation": "劳动保护"}, {"phrase": "safety protection", "translation": "安全防护"}, {"phrase": "differential protection", "translation": "差动保护；比例制动式纵差保护"}, {"phrase": "patent protection", "translation": "专利保护"}, {"phrase": "slope protection", "translation": "边坡保护，护坡；护坡工程"}, {"phrase": "under the protection of", "translation": "在…的保护下"}, {"phrase": "plant protection", "translation": "植物保护；工厂保护"}, {"phrase": "consumer protection", "translation": "消费者保护"}, {"phrase": "radiation protection", "translation": "【核】辐射防护"}]}