{"word": "provide", "levels": ["cet4", "junior", "postgraduate", "senior"], "translations": [{"translation": "提供；装备，供给", "types": ["v"]}, {"translation": "提供， 供给", "types": ["vt"]}, {"translation": "提供；规定；准备；装备", "types": ["v"]}, {"translation": "供应， 提供", "types": ["v"]}, {"translation": "供应,供给,准备,预防,规定", "types": ["v"]}, {"translation": "提供", "types": ["v"]}], "phrases": [{"phrase": "provide oneself", "translation": "自备；自办"}, {"phrase": "provide for", "translation": "供养，供给；规定；为…作准备"}, {"phrase": "provide service", "translation": "提供服务"}, {"phrase": "provide with", "translation": "供给"}, {"phrase": "provide against", "translation": "规定禁止；预防"}]}