{"word": "punch", "levels": ["cet4", "cet6", "postgraduate", "toefl"], "translations": [{"translation": "冲出", "types": ["v"]}, {"translation": "冲压机", "types": ["n"]}, {"translation": "猛击；穿孔", "types": ["vt"]}, {"translation": "猛击； 冲床； 穿孔机； 力量， 效力", "types": ["n"]}, {"translation": "打孔", "types": ["v"]}, {"translation": "冲压机；打洞器；钻孔机", "types": ["n"]}, {"translation": "开洞；以拳重击", "types": ["v"]}, {"translation": "冲压机， 冲床；穿孔机", "types": ["n"]}, {"translation": "拳击； 冲压； 穿孔", "types": ["vt"]}, {"translation": "冲孔, 打孔", "types": ["v"]}, {"translation": "拳打；打孔；按，压", "types": ["vt"]}, {"translation": "重拳击打； 冲床， 打孔机", "types": ["n"]}], "phrases": [{"phrase": "punch in", "translation": "上班打卡"}, {"phrase": "punch card", "translation": "穿孔卡片（等于punched card）"}, {"phrase": "punch press", "translation": "冲床；压力机"}, {"phrase": "punch line", "translation": "n. 妙语"}, {"phrase": "punch machine", "translation": "打卡机；冲孔机"}, {"phrase": "pack a punch", "translation": "◎拳头凶猛有力，能击出有力的一拳"}, {"phrase": "punch out", "translation": "下班打卡"}, {"phrase": "as pleased as punch", "translation": "非常高傲；得意洋洋"}, {"phrase": "hole punch", "translation": "打孔机；打孔"}, {"phrase": "punch through", "translation": "【物】穿通现象"}, {"phrase": "punch on", "translation": "穿孔开始"}, {"phrase": "one-two punch", "translation": "连环出击；连续左右猛击；连续出击的组合拳"}, {"phrase": "punch forming", "translation": "【化】冲压成型"}, {"phrase": "fruit punch", "translation": "果汁喷趣酒（清凉饮料）；水果混合饮料"}, {"phrase": "punch hole", "translation": "【信息工程】穿孔"}]}