{"word": "remove", "levels": ["cet4", "cet6", "postgraduate", "senior", "toefl"], "translations": [{"translation": "消除，移除", "types": ["v"]}, {"translation": "移动，搬开；脱掉", "types": ["v"]}, {"translation": "消除，移除；更新", "types": ["v"]}, {"translation": "移动,脱掉,调动,免职", "types": ["v"]}, {"translation": "移动，迁移；开除；调动", "types": ["v"]}, {"translation": "移动；距离；搬家", "types": ["n"]}, {"translation": "移动， 拿走； 去除", "types": ["vt"]}, {"translation": "移开,去除", "types": ["v"]}], "phrases": [{"phrase": "remove oneself", "translation": "【戏谑语】挪动挪动;走开,离开：\n\nShe removed herself reluctantly.\n她勉强地走开了。"}, {"phrase": "remove all", "translation": "删除所有；全部移除"}, {"phrase": "remove from", "translation": "除掉；移动"}, {"phrase": "at one remove", "translation": "隔一代（之嫡亲）"}]}