{"word": "resolve", "levels": ["cet4", "cet6", "postgraduate", "toefl"], "translations": [{"translation": "解决，下决心", "types": ["v"]}, {"translation": "解决；决心", "types": ["v"]}, {"translation": "决心", "types": ["n"]}, {"translation": "解决， 解答； 决定， 决意", "types": ["n", "v"]}, {"translation": "决定；解决；分解", "types": ["v"]}, {"translation": "决心;（使）分解,溶解;决议", "types": ["v"]}, {"translation": "解决;决心", "types": ["n"]}, {"translation": "决定；溶解；使…分解；决心要做…", "types": ["v"]}, {"translation": "坚决；决定要做的事", "types": ["n"]}, {"translation": "决心， 决定 <；分解， 溶解；决议；解决", "types": ["v"]}, {"translation": "解决， 解答；决心；决议", "types": ["n"]}, {"translation": "解决, 决定", "types": ["v"]}, {"translation": "解决；决定，决心；分解；显现", "types": ["v"]}, {"translation": "决心， 决议", "types": ["n"]}], "phrases": [{"phrase": "resolve into", "translation": "使分解为…；归结为"}, {"phrase": "fail to resolve", "translation": "解决未果"}]}