{"word": "some", "levels": ["junior", "senior"], "translations": [{"translation": "一些；某个；大约；相当多的", "types": ["adj"]}, {"translation": "一些；若干；其中的一部分；（数量不确切时用）有些人", "types": ["pron"]}, {"translation": "非常；相当；<美>稍微", "types": ["adv"]}, {"translation": "大约； 稍微", "types": ["adv"]}, {"translation": "一些，若干", "types": ["pron"]}, {"translation": "一些，若干，有些；某个，某一", "types": ["adj"]}, {"translation": "若干， 一些", "types": ["pron"]}, {"translation": "一些，若干；有些；某一", "types": ["adj"]}], "phrases": [{"phrase": "some of", "translation": "一些"}, {"phrase": "some of them", "translation": "他们中的一些"}, {"phrase": "some one", "translation": "有人；某人"}, {"phrase": "go some", "translation": "【美国口语】"}]}