{"word": "song", "levels": ["junior", "postgraduate", "senior", "toefl"], "translations": [{"translation": "歌曲；歌唱；诗歌；鸣声", "types": ["n"]}, {"translation": "歌， 歌曲； 鸣声， 歌声", "types": ["n"]}, {"translation": "歌（曲）", "types": ["n"]}], "phrases": [{"phrase": "song dynasty", "translation": "宋朝"}, {"phrase": "folk song", "translation": "民歌"}, {"phrase": "sing a song", "translation": "唱一首歌，唱支歌"}, {"phrase": "theme song", "translation": "主题歌；信号曲；老套话"}, {"phrase": "song and dance", "translation": "不着边际的废话；大肆宣扬"}, {"phrase": "love song", "translation": "情歌"}, {"phrase": "popular song", "translation": "n. 流行歌曲"}, {"phrase": "pop song", "translation": "流行歌曲；流行曲"}, {"phrase": "for a song", "translation": "非常便宜地；廉价地"}, {"phrase": "song of praise", "translation": "赞歌"}, {"phrase": "original song", "translation": "原创歌曲"}, {"phrase": "song of solomon", "translation": "【宗】雅歌"}, {"phrase": "art song", "translation": "艺术歌曲"}, {"phrase": "swan song", "translation": "绝笔，最后的作品；天鹅临死时的叫声"}, {"phrase": "hit song", "translation": "流行一时的歌曲"}, {"phrase": "song of songs", "translation": "n. 歌中之歌；雅歌：旧约圣经中之一部，以诗歌方式描述天人之间的爱。；所罗门之歌"}, {"phrase": "burst into song", "translation": "忽然唱起歌来"}, {"phrase": "work song", "translation": "劳动号子；工作歌"}, {"phrase": "song and dance drama", "translation": "歌舞剧"}, {"phrase": "campus song", "translation": "n. 校园歌曲"}]}