{"word": "sort", "levels": ["cet4", "junior", "postgraduate", "senior", "toefl"], "translations": [{"translation": "种类；类别", "types": ["n"]}, {"translation": "整理", "types": ["v"]}, {"translation": "种类；方式；品质", "types": ["n"]}, {"translation": "分类；协调；交往", "types": ["v"]}, {"translation": "分类， 整理", "types": ["v"]}, {"translation": "种类，类别；某一种人，某一类人", "types": ["n"]}, {"translation": "分类，拣选", "types": ["v"]}, {"translation": "种类， 类别", "types": ["n"]}, {"translation": "种类v分类,拣选", "types": ["n"]}], "phrases": [{"phrase": "sort of", "translation": "有几分地；到某种程度；稍稍"}, {"phrase": "some sort of", "translation": "某种的；多少有些；仿佛"}, {"phrase": "sort out", "translation": "挑选出"}, {"phrase": "of sorts", "translation": "各种各样的"}, {"phrase": "that sort of thing", "translation": "那类事情"}, {"phrase": "of a sort", "translation": "同一种类的"}, {"phrase": "quick sort", "translation": "快速分类"}, {"phrase": "sort order", "translation": "【计】排序次序"}, {"phrase": "bubble sort", "translation": "冒泡排序；上推分类法"}, {"phrase": "sort by", "translation": "排序方式"}, {"phrase": "out of sorts", "translation": "心情不佳；身体不适；不高兴的"}, {"phrase": "sort through", "translation": "分类，整理"}, {"phrase": "insertion sort", "translation": "插入分类"}, {"phrase": "heap sort", "translation": "群分类；堆分类"}, {"phrase": "merge sort", "translation": "合并分类；归并排序"}, {"phrase": "selection sort", "translation": "选择排序法；选择分类排序"}, {"phrase": "in some sort", "translation": "adv. 稍微"}, {"phrase": "sort ascending", "translation": "n. 【计】升序"}, {"phrase": "a good sort", "translation": "好人"}, {"phrase": "sort descending", "translation": "降序"}]}