{"word": "suspicion", "levels": ["cet4", "cet6", "postgraduate", "sat", "toefl"], "translations": [{"translation": "怀疑，疑心，猜疑", "types": ["n"]}, {"translation": "怀疑， 疑心， 猜疑； 一点儿， 少量", "types": ["n"]}, {"translation": "怀疑，猜疑；一点儿，少量", "types": ["n"]}, {"translation": "猜疑， 怀疑", "types": ["n"]}, {"translation": "怀疑；嫌疑；疑心；一点儿", "types": ["n"]}, {"translation": "怀疑", "types": ["vt"]}, {"translation": "怀疑， 猜疑", "types": ["n"]}, {"translation": "猜疑, 怀疑", "types": ["n"]}], "phrases": [{"phrase": "on suspicion", "translation": "因嫌疑；根据猜想"}, {"phrase": "on suspicion of", "translation": "有嫌疑"}, {"phrase": "with suspicion", "translation": "怀疑地"}, {"phrase": "under suspicion", "translation": "受嫌疑"}, {"phrase": "above suspicion", "translation": "无可怀疑"}]}