{"word": "taste", "levels": ["cet4", "junior", "postgraduate", "senior", "toefl"], "translations": [{"translation": "味觉，品味", "types": ["n"]}, {"translation": "味道；品味；审美", "types": ["n"]}, {"translation": "尝；体验", "types": ["v"]}, {"translation": "有…味道； 品尝； 体验， 感受", "types": ["v"]}, {"translation": "滋味；味觉，口味；鉴赏力；兴趣，爱好", "types": ["n"]}, {"translation": "喜爱，爱好，口味", "types": ["n"]}, {"translation": "有…的味道", "types": ["v"]}, {"translation": "品尝, 体验", "types": ["v"]}], "phrases": [{"phrase": "taste of", "translation": "体验；有…味道"}, {"phrase": "good taste", "translation": "高品味；味道纯正"}, {"phrase": "in taste", "translation": "得体的，大方的；高雅的，有礼的"}, {"phrase": "taste for", "translation": "对…的喜爱；对…的爱好"}, {"phrase": "sweet taste", "translation": "甜味"}, {"phrase": "bitter taste", "translation": "味苦，苦味"}, {"phrase": "bad taste", "translation": "低级趣味，粗俗；坏品味"}, {"phrase": "have a taste", "translation": "尝一尝；品尝一下"}, {"phrase": "sharp taste", "translation": "辛辣味"}, {"phrase": "taste of life", "translation": "生活的滋味"}, {"phrase": "sense of taste", "translation": "味觉"}, {"phrase": "in good taste", "translation": "大方的；得体的"}, {"phrase": "sour taste", "translation": "酸味；口酸"}, {"phrase": "taste note", "translation": "品酒记录"}, {"phrase": "acquired taste", "translation": "嗜好；爱好"}, {"phrase": "taste bud", "translation": "【解】味蕾"}, {"phrase": "have a taste for", "translation": "爱好；对…有兴趣"}, {"phrase": "refined taste", "translation": "高雅的品味"}, {"phrase": "pungent taste", "translation": "刺激味；辛辣味"}, {"phrase": "in bad taste", "translation": "不礼貌；粗俗"}]}