{"word": "thinking", "levels": ["cet4", "senior"], "translations": [{"translation": "深思的， 有理性的", "types": ["adj"]}, {"translation": "想法，意见，见解", "types": ["n"]}, {"translation": "思考的；思想的；有理性的；好思考的", "types": ["adj"]}, {"translation": "思考；思想；想法；意见；见解", "types": ["n"]}, {"translation": "思考（think的现在分词）", "types": ["v"]}, {"translation": "思索； 见解； 想法", "types": ["n"]}], "phrases": [{"phrase": "thinking of", "translation": "想起"}, {"phrase": "way of thinking", "translation": "思维方式；看法，视角"}, {"phrase": "creative thinking", "translation": "创造性思维"}, {"phrase": "mode of thinking", "translation": "思维方式；思考模式"}, {"phrase": "critical thinking", "translation": "批判性思维，批判性的思考；批判思考能力，判断思维"}, {"phrase": "strategic thinking", "translation": "战略思维；战略思想；策略性思考"}, {"phrase": "logical thinking", "translation": "逻辑思维，逻辑思考"}, {"phrase": "independent thinking", "translation": "独立思考"}, {"phrase": "rational thinking", "translation": "理性思维"}, {"phrase": "wishful thinking", "translation": "n. 如意算盘；痴心妄想"}, {"phrase": "thinking process", "translation": "思维过程"}, {"phrase": "quick thinking", "translation": "思考迅速，敏捷的思维"}, {"phrase": "thinking model", "translation": "思维模式"}, {"phrase": "abstract thinking", "translation": "抽象思维；抽象思考能力"}, {"phrase": "philosophic thinking", "translation": "哲学思想"}, {"phrase": "divergent thinking", "translation": "发散思维，扩散思考"}, {"phrase": "good thinking", "translation": "n. 好主意；好思维；聪明极了"}, {"phrase": "visual thinking", "translation": "视觉思维；视觉思考"}, {"phrase": "system thinking", "translation": "系统思考，系统思想"}, {"phrase": "thinking aloud", "translation": "【心理学】出声思维；放声思考"}]}