{"word": "trail", "levels": ["cet4", "postgraduate", "toefl"], "translations": [{"translation": "痕迹；小径", "types": ["n"]}, {"translation": "跟踪", "types": ["v"]}, {"translation": "痕迹，小径", "types": ["n"]}, {"translation": "跟踪， 追踪", "types": ["vt"]}, {"translation": "追踪；拖；蔓延；落后于", "types": ["v"]}, {"translation": "小径；痕迹；尾部；踪迹；一串，一系列", "types": ["n"]}, {"translation": "踪迹， 痕迹；小道", "types": ["n"]}, {"translation": "追踪， 跟踪", "types": ["vt"]}, {"translation": "踪迹", "types": ["n"]}, {"translation": "追踪", "types": ["v"]}], "phrases": [{"phrase": "on the trail", "translation": "追踪，寻找；在山径上"}, {"phrase": "audit trail", "translation": "审查跟踪，尾随审查；查帐索引；逐位跟踪"}, {"phrase": "follow the trail", "translation": "顺着足迹"}, {"phrase": "in trail", "translation": "adv. 成一列纵队；挨次"}, {"phrase": "on the trail of", "translation": "跟踪追赶"}, {"phrase": "paper trail", "translation": "书面记录"}, {"phrase": "blaze a trail", "translation": "开辟道路；在树上作记号指路"}, {"phrase": "nature trail", "translation": "通往自然景观的小径"}, {"phrase": "off the trail", "translation": "出轨；失去踪迹；偏离目标"}, {"phrase": "appalachian trail", "translation": "阿巴拉契亚山道；阿帕拉契山径"}, {"phrase": "on trail", "translation": "受审；试行；在实验中"}]}