{"word": "triumph", "levels": ["cet4", "cet6", "postgraduate", "sat", "toefl"], "translations": [{"translation": "胜利", "types": ["n"]}, {"translation": "凯旋；胜利", "types": ["n"]}, {"translation": "成功", "types": ["v"]}, {"translation": "成功", "types": ["vi"]}, {"translation": "凯旋，胜利", "types": ["n"]}, {"translation": "胜利，凯旋；欢欣", "types": ["n"]}, {"translation": "获得胜利，成功", "types": ["v"]}, {"translation": "得胜， 战胜", "types": ["vi"]}, {"translation": "胜利， 成功", "types": ["n"]}, {"translation": "狂喜； 胜利， 成功", "types": ["n"]}, {"translation": "获胜", "types": ["v"]}, {"translation": "获胜， 成功", "types": ["v"]}, {"translation": "狂喜；胜利，成功", "types": ["n"]}], "phrases": [{"phrase": "in triumph", "translation": "胜利地；洋洋得意地；耀武扬威地"}, {"phrase": "triumph over", "translation": "击败；得胜；成功"}]}