{"word": "trivial", "levels": ["cet6", "postgraduate", "sat", "toefl"], "translations": [{"translation": "琐碎的；平常的", "types": ["adj"]}, {"translation": "琐碎的， 不重要的", "types": ["adj"]}, {"translation": "不重要的，琐碎的；琐细的", "types": ["adj"]}, {"translation": "琐碎的； 无足轻重的  <", "types": ["adj"]}, {"translation": "琐碎的； 无足轻重的", "types": ["adj"]}, {"translation": "琐碎的，不重要的", "types": ["adj"]}, {"translation": "琐碎的， 微不足道的", "types": ["adj"]}], "phrases": [{"phrase": "trivial matters", "translation": "无关重要的事情（trivial matter的复数形式）"}]}