{"word": "video", "levels": ["cet4", "cet6", "junior", "postgraduate", "senior", "toefl"], "translations": [{"translation": "录像的；电视的", "types": ["adj"]}, {"translation": "录像", "types": ["n"]}, {"translation": "录像的", "types": ["adj"]}, {"translation": "【电子】 视频；录像，录像机；电视", "types": ["n"]}, {"translation": "视频的；录像的；电视的", "types": ["adj"]}, {"translation": "录制", "types": ["v"]}, {"translation": "制作…的录像", "types": ["v"]}, {"translation": "录像；录像带", "types": ["n"]}, {"translation": "电视,视频;录像", "types": ["n"]}, {"translation": "电视的,视频的;录像的", "types": ["adj"]}, {"translation": "电视的； 视频的；录像的", "types": ["adj"]}, {"translation": "电视； 视频；录像", "types": ["n"]}, {"translation": "录象, 视频 a视频的", "types": ["n"]}], "phrases": [{"phrase": "digital video", "translation": "数字视频，数字录像"}, {"phrase": "video game", "translation": "视频游戏；电视游戏"}, {"phrase": "video frequency", "translation": "视频率"}, {"phrase": "video camera", "translation": "摄影机"}, {"phrase": "video signal", "translation": "视频信号"}, {"phrase": "video conferencing", "translation": "电视会议"}, {"phrase": "video conference", "translation": "视讯会议；电视会议"}, {"phrase": "video recording", "translation": "录象；显像记录"}, {"phrase": "video transmission", "translation": "视频传输；视频发送"}, {"phrase": "video compression", "translation": "视频压缩；视讯压缩；图象压缩"}, {"phrase": "video capture", "translation": "视频捕捉"}, {"phrase": "video clip", "translation": "视频剪辑；视讯片段"}, {"phrase": "music video", "translation": "音乐录影带；音乐视频片；音乐视讯片"}, {"phrase": "video processing", "translation": "视频加工"}, {"phrase": "video card", "translation": "视频卡"}, {"phrase": "video tape", "translation": "录像磁带"}, {"phrase": "video equipment", "translation": "视频设备；录像设备，录放影设备；视觉器材"}, {"phrase": "video display", "translation": "n. 视频显示；视频显示器"}, {"phrase": "video monitor", "translation": "显示器；视频监视器"}, {"phrase": "video quality", "translation": "视频质量"}]}